{
  "date": "2026-07-04",
  "source": "Wikipedia: Portál:Aktuality + Portal:Current events (CC BY-SA 4.0)",
  "sourceUrl": "https://en.wikipedia.org/wiki/Portal:Current_events/2026_July_4",
  "translator": "MyMemory",
  "stories": [
    {
      "it": "La Russia ha chiuso diversi valichi di frontiera ferroviari con Finlandia, Estonia e Lettonia.",
      "cz": "Rusko uzavřelo několik železničních hraničních přechodů do Finska, Estonska a Lotyšska.",
      "origin": "cz"
    },
    {
      "it": "La Slovacchia ha assunto la presidenza del Gruppo di Visegrad per un anno.",
      "cz": "Slovensko na jeden rok převzalo předsednictví Visegrádské skupiny.",
      "origin": "cz"
    },
    {
      "it": "Il decreto governativo ha esteso i poteri dei medici di medicina generale che, come gli specialisti, possono prescrivere farmaci per alcune malattie croniche.",
      "cz": "Vládní vyhláška rozšířila praktickým lékařům pravomoci a mohou podobně jako specialisté předepisovat léky na některé chronické nemoci.",
      "origin": "cz"
    }
  ],
  "article": null,
  "shadow": {
    "it": "La Slovacchia ha assunto la presidenza del Gruppo di Visegrad per un anno.",
    "cz": "Slovensko na jeden rok převzalo předsednictví Visegrádské skupiny.",
    "phon": "[la slo-VÁK-kia a as-SÚN-to la pre-zi-DÉN-ca del GRÚP-po di vi-ZÉG-rad per un ÁN-no]"
  }
}
